[
  {
    "name": "cid",
    "dataset": "phrf",
    "label": "Case-ID, Original Household Number",
    "categories": {
      "values": [],
      "labels": [],
      "missings": [],
      "frequencies": []
    },
    "scale": "number",
    "label_de": "Ursprungshaushaltsnummer",
    "study": "soep-core",
    "statistics": {
      "Min.": 200034.0,
      "1st Qu.": 879819.0,
      "Median": 959708.0,
      "Mean": 2160045.9331062404,
      "3rd Qu.": 4068632.0,
      "Max.": 4173037.0,
      "valid": 40512,
      "invalid": 0
    }
  },
  {
    "name": "hid",
    "dataset": "phrf",
    "label": "Current Wave HH Number",
    "categories": {
      "values": [],
      "labels": [],
      "missings": [],
      "frequencies": []
    },
    "scale": "number",
    "label_de": "Aktuelle Haushaltsnummer",
    "study": "soep-core",
    "statistics": {
      "Min.": 115380.0,
      "1st Qu.": 883891.0,
      "Median": 957275.0,
      "Mean": 2141510.585308057,
      "3rd Qu.": 4067781.5,
      "Max.": 4173037.0,
      "valid": 40512,
      "invalid": 0
    }
  },
  {
    "name": "pid",
    "dataset": "phrf",
    "label": "Never Changing Person ID",
    "categories": {
      "values": [],
      "labels": [],
      "missings": [],
      "frequencies": []
    },
    "scale": "number",
    "label_de": "Unveraenderliche Personennummer",
    "study": "soep-core",
    "statistics": {
      "Min.": 1153802.0,
      "1st Qu.": 8806504.0,
      "Median": 9589302.0,
      "Mean": 21562373.345724724,
      "3rd Qu.": 40683302.25,
      "Max.": 41730304.0,
      "valid": 40512,
      "invalid": 0
    }
  },
  {
    "name": "syear",
    "dataset": "phrf",
    "label": "Survey Year",
    "categories": {
      "values": [],
      "labels": [],
      "missings": [],
      "frequencies": []
    },
    "scale": "number",
    "label_de": "Befragungsjahr",
    "study": "soep-core",
    "statistics": {
      "Min.": 2011.0,
      "1st Qu.": 2013.0,
      "Median": 2015.0,
      "Mean": 2014.4894845971564,
      "3rd Qu.": 2016.0,
      "Max.": 2017.0,
      "valid": 40512,
      "invalid": 0
    }
  },
  {
    "name": "pbleib",
    "dataset": "phrf",
    "label": "Inverse Staying Probability",
    "categories": {
      "values": [],
      "labels": [],
      "missings": [],
      "frequencies": []
    },
    "scale": "number",
    "label_de": "Inverse Bleibewahrscheinlichkeit",
    "study": "soep-core",
    "statistics": {
      "Min.": 0.0,
      "1st Qu.": 1.0,
      "Median": 1.08,
      "Mean": 0.9361159657997683,
      "3rd Qu.": 1.18,
      "Max.": 5.070000171661377,
      "valid": 40512,
      "invalid": 0
    }
  },
  {
    "name": "phrf",
    "dataset": "phrf",
    "label": "Weighting Factor",
    "categories": {
      "values": [],
      "labels": [],
      "missings": [],
      "frequencies": []
    },
    "scale": "number",
    "label_de": "Hochrechnungsfaktor",
    "study": "soep-core",
    "statistics": {
      "Min.": 175.45268979559168,
      "1st Qu.": 6963.560710208776,
      "Median": 10711.702292424183,
      "Mean": 13945.46027703753,
      "3rd Qu.": 16754.875328117265,
      "Max.": 224569.2199809052,
      "valid": 40512,
      "invalid": 0
    }
  }
]